chatGPT_debugger/__init__.py
chatGPT_debugger/callAPI.py
chatGPT_debugger/chatGPT_debugger.py
chatGPT_debugger/engine.py
chatGPT_debugger/is_wrapped.py
chatGPT_debugger/store_api_key.py
chatGPT_debugger-0.1.3.dist-info/LICENSE
chatGPT_debugger-0.1.3.dist-info/METADATA
chatGPT_debugger-0.1.3.dist-info/WHEEL
chatGPT_debugger-0.1.3.dist-info/top_level.txt
chatGPT_debugger-0.1.3.dist-info/RECORD
