Metadata-Version: 2.1
Name: chatGPT-debugger
Version: 0.1.3
Summary: Debug Python code with ChatGPT3 and get error explanations and corrected code.
Home-page: https://github.com/JimmyAllison
Author: 5-MinutePython(Jimmy Allison)
Author-email: 5minutepython2@gmail.com
Classifier: Programming Language :: Python :: 3
Classifier: License :: OSI Approved :: MIT License
Classifier: Operating System :: OS Independent
Requires-Python: >=3.7
License-File: LICENSE
Requires-Dist: openai
Requires-Dist: keyring
